decisiontelecom/__init__.py
decisiontelecom/sms.py
decisiontelecom/viber.py
decisiontelecom/viber_plus_sms.py
tests/__init__.py
tests/test_sms.py
tests/test_viber.py
tests/test_viber_plus_sms.py
decisiontelecom-1.0.0.dist-info/LICENSE
decisiontelecom-1.0.0.dist-info/METADATA
decisiontelecom-1.0.0.dist-info/WHEEL
decisiontelecom-1.0.0.dist-info/top_level.txt
decisiontelecom-1.0.0.dist-info/RECORD
