Metadata-Version: 2.1
Name: decisiontelecom
Version: 1.0.0
Summary: A Python client library for IT-Decision Telecom messaging API
Home-page: https://github.com/IT-DecisionTelecom/DecisionTelecom-Python
Author: IT-Decision Telecom
Author-email: info@it-decision.com
License: MIT
Keywords: decisiontelecom,sms,viber,messaging
Platform: UNKNOWN
Classifier: Programming Language :: Python :: 3
Classifier: License :: OSI Approved :: MIT License
Classifier: Operating System :: OS Independent
License-File: LICENSE
Requires-Dist: requests (>=2.27.1)
Provides-Extra: dev
Requires-Dist: unittest ; extra == 'dev'
Requires-Dist: responses ; extra == 'dev'
